django_excel_response/__init__.py
django_excel_response/excel_response.py
django_excel_response2-3.0.6.dist-info/METADATA
django_excel_response2-3.0.6.dist-info/WHEEL
django_excel_response2-3.0.6.dist-info/top_level.txt
django_excel_response2-3.0.6.dist-info/RECORD
