Metadata-Version: 2.1
Name: django-excel-response2
Version: 3.0.6
Summary: A function extends of Tarken's django-excel-response
Home-page: https://github.com/django-xxx/django-excel-response2
Author: Hackathon
Author-email: kimi.huang@brightcells.com
Keywords: django-excel-response django-excel-response2
Classifier: Development Status :: 5 - Production/Stable
Classifier: Environment :: Web Environment
Classifier: Framework :: Django
Classifier: Intended Audience :: Developers
Classifier: Programming Language :: Python
Classifier: Topic :: Software Development :: Libraries :: Python Modules
Classifier: Topic :: Office/Business :: Financial :: Spreadsheet
